cota/__init__.py
cota/__main__.py
cota/actions/__init__.py
cota/actions/action.py
cota/actions/bot_utter.py
cota/actions/constant.py
cota/actions/executors/base.py
cota/actions/executors/http.py
cota/actions/executors/mcp.py
cota/actions/executors/plugin.py
cota/actions/executors/python.py
cota/actions/executors/script.py
cota/actions/form.py
cota/actions/plugins/base.py
cota/actions/plugins/example.py
cota/actions/rag.py
cota/actions/selector.py
cota/actions/user_utter.py
cota/agent.py
cota/bots/pet/README.md
cota/bots/pet/agent.yml
cota/bots/pet/endpoints.yml
cota/bots/pet/policy/data.yml
cota/bots/weather/README.md
cota/bots/weather/agent.yml
cota/bots/weather/endpoints.yml
cota/bots/weather/policy/data.yml
cota/bots/weather/policy/rules.yml
cota/channels/__init__.py
cota/channels/channel.py
cota/channels/cmdline.py
cota/channels/connection.py
cota/channels/room.py
cota/channels/socketio.py
cota/channels/sse.py
cota/channels/utils.py
cota/channels/websocket.py
cota/constant.py
cota/dpl/__init__.py
cota/dpl/dpl.py
cota/dpl/llm.py
cota/dpl/match.py
cota/dpl/trigger.py
cota/dst.py
cota/knowledge/__init__.py
cota/knowledge/knowledge.py
cota/knowledge/llm_knowledge.py
cota/llm/__init__.py
cota/llm/base.py
cota/llm/custom.py
cota/llm/factory.py
cota/llm/llm.py
cota/llm/openai.py
cota/message/message.py
cota/processor.py
cota/server.py
cota/store.py
cota/task.py
cota/utils/__init__.py
cota/utils/common.py
cota/utils/http/__init__.py
cota/utils/http/client.py
cota/utils/http/manager.py
cota/utils/io.py
cota/utils/parser.py
cota-1.1.1.dist-info/METADATA
cota-1.1.1.dist-info/WHEEL
cota-1.1.1.dist-info/entry_points.txt
cota-1.1.1.dist-info/licenses/LICENSE
cota-1.1.1.dist-info/RECORD
