Metadata-Version: 2.4
Name: cota
Version: 1.1.1
Summary: Chain of Thought Agent Platform for Industrial-Grade Dialogue Systems
License: MIT
License-File: LICENSE
Keywords: chatbot,dialogue,agent,llm,chain-of-thought
Author: MingGuangShao
Author-email: 690714362@qq.com
Requires-Python: >=3.12
Classifier: Development Status :: 4 - Beta
Classifier: Intended Audience :: Developers
Classifier: License :: OSI Approved :: MIT License
Classifier: Programming Language :: Python :: 3
Classifier: Programming Language :: Python :: 3.12
Classifier: Programming Language :: Python :: 3.13
Classifier: Programming Language :: Python :: 3.14
Classifier: Topic :: Scientific/Engineering :: Artificial Intelligence
Classifier: Topic :: Software Development :: Libraries :: Python Modules
Requires-Dist: aiohttp (>=3.9,<4.0)
Requires-Dist: asyncio (>=3.4.3,<4.0.0)
Requires-Dist: cpm-kernels (>=1.0.11,<2.0.0)
Requires-Dist: dashscope (>=1.20.0)
Requires-Dist: gunicorn (>=21.2.0,<22.0.0)
Requires-Dist: httpx (>=0.27.0,<0.28.0)
Requires-Dist: mcp (>=1.0.0,<2.0.0)
Requires-Dist: numpy (>=1.21.4,<2.0.0)
Requires-Dist: openai (>=1.31.1)
Requires-Dist: protobuf (>=4.22.1,<5.0.0)
Requires-Dist: psycopg2-binary (>=2.9.9,<3.0.0)
Requires-Dist: pymysql (>=1.1.1,<2.0.0)
Requires-Dist: pytest (>=7.3.1,<8.0.0)
Requires-Dist: python-socketio (>=4.4,<6)
Requires-Dist: pyyaml (>=6.0.1,<7.0.0)
Requires-Dist: questionary (>=1.5.1,<1.11.0)
Requires-Dist: sanic (>=23.12,<23.13)
Requires-Dist: sanic-cors (>=2.0.0,<2.1.0)
Requires-Dist: sanic-jwt (>=1.6.0,<2.0.0)
Requires-Dist: sanic-routing (>=23.12.0)
Requires-Dist: setuptools (>=70.1.1,<71.0.0)
Requires-Dist: sqlalchemy (>=2.0.22,<3.0.0)
Requires-Dist: websockets (>=10.0,<11.0)
Project-URL: Documentation, https://cotaai.github.io/cota/
Project-URL: Homepage, https://github.com/CotaAI/cota
Project-URL: Repository, https://github.com/CotaAI/cota
